odoo/addons/sale_stock_sourcing_address/README.rst
odoo/addons/sale_stock_sourcing_address/__init__.py
odoo/addons/sale_stock_sourcing_address/__manifest__.py
odoo/addons/sale_stock_sourcing_address/i18n/ca.po
odoo/addons/sale_stock_sourcing_address/i18n/es.po
odoo/addons/sale_stock_sourcing_address/i18n/sale_stock_sourcing_address.pot
odoo/addons/sale_stock_sourcing_address/models/__init__.py
odoo/addons/sale_stock_sourcing_address/models/account_invoice_line.py
odoo/addons/sale_stock_sourcing_address/models/sale_order_line.py
odoo/addons/sale_stock_sourcing_address/readme/CONFIGURE.rst
odoo/addons/sale_stock_sourcing_address/readme/CONTRIBUTORS.rst
odoo/addons/sale_stock_sourcing_address/readme/DESCRIPTION.rst
odoo/addons/sale_stock_sourcing_address/security/security.xml
odoo/addons/sale_stock_sourcing_address/static/description/icon.png
odoo/addons/sale_stock_sourcing_address/static/description/index.html
odoo/addons/sale_stock_sourcing_address/tests/__init__.py
odoo/addons/sale_stock_sourcing_address/tests/test_sale_stock_sourcing_address.py
odoo/addons/sale_stock_sourcing_address/views/account_invoice_view.xml
odoo/addons/sale_stock_sourcing_address/views/sale_order_view.xml
odoo13_addon_sale_stock_sourcing_address-13.0.1.0.1.dist-info/METADATA
odoo13_addon_sale_stock_sourcing_address-13.0.1.0.1.dist-info/WHEEL
odoo13_addon_sale_stock_sourcing_address-13.0.1.0.1.dist-info/top_level.txt
odoo13_addon_sale_stock_sourcing_address-13.0.1.0.1.dist-info/RECORD
